LICENSE
MANIFEST.in
README
setup.py
lmiapi/__init__.py
lmiapi/v1.py
lmiapi.egg-info/PKG-INFO
lmiapi.egg-info/SOURCES.txt
lmiapi.egg-info/dependency_links.txt
lmiapi.egg-info/not-zip-safe
lmiapi.egg-info/requires.txt
lmiapi.egg-info/top_level.txt